{
  "name": "ccv3-polish-translation",
  "displayName": "CCv3 Polish Translation",
  "description": "Polskie slowa kluczowe dla skill-rules.json (V6.1) - slang, diakrytyki, intentPatterns",
  "version": "2.0.0",
  "platform": "any",
  "author": "kmylpenter",
  "dependencies": {},
  "targets": {},
  "postInstall": null,
  "notes": "UWAGA: Nadpisuje skill-rules.json. V6.1: 100% testow, slang PL (wrzuc/ogarnij/schrzanilo), intentPatterns dla zapisz/kontynuuj, regresja EN naprawiona.",
  "scripts": {
    "postinstall": "python3 %ADDON_DIR%/merge_skill_rules.py %ADDON_DIR%/files/skills/skill-rules.json"
  }
}
